python_state_machine/__init__.py
python_state_machine/models/__init__.py
python_state_machine/orm/__init__.py
python_state_machine/orm/base.py
python_state_machine-0.0.18.dist-info/LICENSE.txt
python_state_machine-0.0.18.dist-info/METADATA
python_state_machine-0.0.18.dist-info/WHEEL
python_state_machine-0.0.18.dist-info/top_level.txt
python_state_machine-0.0.18.dist-info/RECORD
