Metadata-Version: 2.1
Name: python-state-machine
Version: 0.0.18
Summary: Simple Python State Machines
Home-page: https://github.com/girante/python_state_machine
Author: Ricardo Rodrigues
Author-email: r.rodrigues@coboc.biz
License: MIT
Platform: UNKNOWN
Classifier: Intended Audience :: Developers
Classifier: License :: OSI Approved :: MIT License
Classifier: Programming Language :: Python :: 2.7
Classifier: Programming Language :: Python :: 3
